filefetcher/__init__.py
filefetcher/cli.py
filefetcher/exceptions.py
filefetcher/manager.py
filefetcher/manifest.py
filefetcher/util.py
filefetcher-0.1.2.dist-info/LICENSE.md
filefetcher-0.1.2.dist-info/METADATA
filefetcher-0.1.2.dist-info/NOTICE.md
filefetcher-0.1.2.dist-info/WHEEL
filefetcher-0.1.2.dist-info/top_level.txt
filefetcher-0.1.2.dist-info/RECORD
