Metadata-Version: 2.1
Name: filefetcher
Version: 0.1.2
Summary: Find, download, and build versioned assets
Home-page: https://github.com/abought/filefetcher
Author: abought
Author-email: abought@umich.edu
License: UNKNOWN
Project-URL: Bug Reports, https://github.com/abought/filefetcher/issues
Project-URL: Source, https://github.com/abought/filefetcher/
Platform: UNKNOWN
Classifier: Development Status :: 3 - Alpha
Classifier: Intended Audience :: Developers
Classifier: License :: OSI Approved :: MIT License
Classifier: Programming Language :: Python :: 3.5
Classifier: Programming Language :: Python :: 3.6
Classifier: Programming Language :: Python :: 3.8
Requires-Python: >=3.5
Provides-Extra: test
Requires-Dist: coverage ; extra == 'test'
Requires-Dist: pytest ; extra == 'test'
Requires-Dist: pytest-flake8 ; extra == 'test'
